setup.py
hello_world/__main__.py
hello_world/foo.py
hello_world_gnits.egg-info/PKG-INFO
hello_world_gnits.egg-info/SOURCES.txt
hello_world_gnits.egg-info/dependency_links.txt
hello_world_gnits.egg-info/entry_points.txt
hello_world_gnits.egg-info/top_level.txt