Metadata-Version: 1.1
Name: hello-world-gnits
Version: 0.0.4
Summary: Hello world
Home-page: https://github.com/ghost-not-in-the-shell/hello-world-gnits
Author: Tang Jiawei
Author-email: tang@o1labs.org
License: UNKNOWN
Platform: UNKNOWN
Classifier: Programming Language :: Python :: 3
Classifier: License :: Freely Distributable
